sbx2imagej/__init__.py
sbx2imagej/sbx2imagej.py
sbx2imagej-0.0.7.dist-info/METADATA
sbx2imagej-0.0.7.dist-info/WHEEL
sbx2imagej-0.0.7.dist-info/entry_points.txt
sbx2imagej-0.0.7.dist-info/top_level.txt
sbx2imagej-0.0.7.dist-info/RECORD
