Metadata-Version: 2.1
Name: sbx2imagej
Version: 0.0.7
Summary: ...
Home-page: https://github.com/orena1/sbx2imagej
Author: Oren Amsalem
Author-email: oren.a4@gmail.com
License: GPL
Requires-Dist: scipy
Requires-Dist: sbxreader
Requires-Dist: pyimagej
Requires-Dist: PyQt5
